MANIFEST.in
README.txt
setup.cfg
setup.py
docs/HISTORY.txt
quintagroup/__init__.py
quintagroup.portlet.pfg.egg-info/PKG-INFO
quintagroup.portlet.pfg.egg-info/SOURCES.txt
quintagroup.portlet.pfg.egg-info/dependency_links.txt
quintagroup.portlet.pfg.egg-info/entry_points.txt
quintagroup.portlet.pfg.egg-info/namespace_packages.txt
quintagroup.portlet.pfg.egg-info/not-zip-safe
quintagroup.portlet.pfg.egg-info/requires.txt
quintagroup.portlet.pfg.egg-info/top_level.txt
quintagroup/portlet/__init__.py
quintagroup/portlet/pfg/__init__.py
quintagroup/portlet/pfg/configure.zcml
quintagroup/portlet/pfg/enableinputlabel.js
quintagroup/portlet/pfg/pfg.pt
quintagroup/portlet/pfg/pfg.pt~
quintagroup/portlet/pfg/pfg.py
quintagroup/portlet/pfg/pfg.py~
quintagroup/portlet/pfg/versions.txt
quintagroup/portlet/pfg/profiles/default/jsregistry.xml
quintagroup/portlet/pfg/profiles/default/metadata.xml
quintagroup/portlet/pfg/profiles/default/portlets.xml
quintagroup/portlet/pfg/tests/__init__.py
quintagroup/portlet/pfg/tests/base.py
quintagroup/portlet/pfg/tests/test_portlet.py