Metadata-Version: 1.0
Name: quintagroup.portlet.pfg
Version: 1.1
Summary: Render form created by PloneFormGen package.
Home-page: http://projects.quintagroup.com/products
Author: Quintagroup
Author-email: support@quintagroup.com
License: GPL
Keywords: portlet pfg
Platform: UNKNOWN
Classifier: Programming Language :: Python
Classifier: Topic :: Software Development :: Libraries :: Python Modules
